rdflib_rif/__init__.py
rdflib_rif/parser.py
rdflib_rif/rif_namespace.py
rdflib_rif/utils.py
rdflib_rif/xmlhandler.py
rdflib_rif/rifpl/__init__.py
rdflib_rif/rifpl/container.py
rdflib_rif/rifpl/container_classes.py
rdflib_rif/rifpl/ebnf.py
rdflib_rif/rifpl/parser.py
rdflib_rif/rifpl/rdflib_parser.py
rdflib_rif/rifxml_validation/__init__.py
rdflib_rif/rifxml_validation/validate_rifxml.py
rdflib_rif/rifxml_validation/schema/__init__.py
tests/__init__.py
tests/conftest.py
tests/test_failed_rdf_parsing.py
tests/test_xmlvalidation.py
tests/data/__init__.py
tests/data/official_examples/__init__.py
tests/data/official_examples/test_compare_official.py
tests/data/official_examples/BLD_NET_Classification_non_inheritance_premise/__init__.py
tests/data/official_examples/BLD_NET_Named_Argument_Uniterms_non_polymorphic_premise/__init__.py
tests/data/official_examples/BLD_NET_OpenLists_premise/__init__.py
tests/data/official_examples/BLD_NET_RDF_Combination_SubClass_5_premise/__init__.py
tests/data/official_examples/BLD_NST_No_free_variables/__init__.py
tests/data/official_examples/BLD_PET_Arbitrary_Entailment_premise/__init__.py
tests/data/official_examples/BLD_PET_Chaining_strategy_numeric_add_2_premise/__init__.py
tests/data/official_examples/BLD_PET_Chaining_strategy_numeric_subtract_1_premise/__init__.py
tests/data/official_examples/BLD_PET_Class_Membership_premise/__init__.py
tests/data/official_examples/BLD_PET_Classification_inheritance_premise/__init__.py
tests/data/official_examples/BLD_PET_ElementEqualityFromListEquality_premise/__init__.py
tests/data/official_examples/BLD_PET_EntailEverything_premise/__init__.py
tests/data/official_examples/BLD_PET_Equality_in_conclusion_1_premise/__init__.py
tests/data/official_examples/BLD_PET_Equality_in_conclusion_2_premise/__init__.py
tests/data/official_examples/BLD_PET_Equality_in_conclusion_3_premise/__init__.py
tests/data/official_examples/BLD_PET_Equality_in_condition_premise/__init__.py
rdflib_rif-0.3.0.dist-info/LICENSE
rdflib_rif-0.3.0.dist-info/METADATA
rdflib_rif-0.3.0.dist-info/WHEEL
rdflib_rif-0.3.0.dist-info/entry_points.txt
rdflib_rif-0.3.0.dist-info/top_level.txt
rdflib_rif-0.3.0.dist-info/RECORD
