Metadata-Version: 2.1
Name: rdflib_rif
Version: 0.3.0
Summary: Parser for rif as plugin for rdflib
Author: Richard Focke Fechner
Author-email: richardfechner@posteo.net
Project-URL: Homepage, https://github.com/WhiteGobo/rdflib_rif
Classifier: Programming Language :: Python :: 3
Classifier: Operating System :: OS Independent
License-File: LICENSE
Requires-Dist: rdflib
Provides-Extra: rifxml_validation
Requires-Dist: lxml ; extra == 'rifxml_validation'
Provides-Extra: test
Requires-Dist: lxml ; extra == 'test'
Requires-Dist: re ; extra == 'test'
Requires-Dist: xml ; extra == 'test'
